vatcheckapi/__init__.py
vatcheckapi/client.py
vatcheckapi-0.1.1.dist-info/METADATA
vatcheckapi-0.1.1.dist-info/WHEEL
vatcheckapi-0.1.1.dist-info/top_level.txt
vatcheckapi-0.1.1.dist-info/RECORD
