Metadata-Version: 2.4
Name: vatcheckapi
Version: 0.1.1
Summary: Python client for the vatcheckapi.com API
Author: 
License: MIT
Project-URL: Homepage, https://vatcheckapi.com/
Classifier: Programming Language :: Python :: 3
Classifier: License :: OSI Approved :: MIT License
Classifier: Operating System :: OS Independent
Requires-Python: >=3.8
Requires-Dist: requests>=2.28
Requires-Dist: typing-extensions>=4.5; python_version < "3.11"
